yaml_to_disk/__init__.py
yaml_to_disk/file_matchers.py
yaml_to_disk/pytest_plugin.py
yaml_to_disk/yaml_to_disk.py
yaml_to_disk/file_types/__init__.py
yaml_to_disk/file_types/base.py
yaml_to_disk/file_types/csv.py
yaml_to_disk/file_types/json.py
yaml_to_disk/file_types/pkl.py
yaml_to_disk/file_types/txt.py
yaml_to_disk/file_types/yaml.py
yaml_to_disk-0.0.3.dist-info/licenses/LICENSE
yaml_to_disk-0.0.3.dist-info/METADATA
yaml_to_disk-0.0.3.dist-info/WHEEL
yaml_to_disk-0.0.3.dist-info/entry_points.txt
yaml_to_disk-0.0.3.dist-info/top_level.txt
yaml_to_disk-0.0.3.dist-info/RECORD
