Metadata-Version: 2.4
Name: yaml_to_disk
Version: 0.0.3
Summary: A simple utility to pretty-print a directory tree, suitable for use in pytest test cases.
Author-email: Matthew McDermott <mattmcdermott8@gmail.com>
Project-URL: Homepage, https://github.com/mmcdermott/yaml_to_disk
Project-URL: Issues, https://github.com/mmcdermott/yaml_to_disk/issues
Classifier: Programming Language :: Python :: 3
Classifier: License :: OSI Approved :: MIT License
Classifier: Operating System :: OS Independent
Requires-Python: >=3.10
License-File: LICENSE
Requires-Dist: pyyaml
Requires-Dist: pytest
Provides-Extra: dev
Requires-Dist: pre-commit<4; extra == "dev"
Requires-Dist: ruff; extra == "dev"
Provides-Extra: tests
Requires-Dist: pytest-cov; extra == "tests"
Requires-Dist: pretty-print-directory; extra == "tests"
Dynamic: license-file
